CHANGES.txt
MANIFEST.in
README.rst
buildout.cfg
setup.py
bobtemplates/__init__.py
bobtemplates/__init__.pyc
bobtemplates.bsuttor.egg-info/PKG-INFO
bobtemplates.bsuttor.egg-info/SOURCES.txt
bobtemplates.bsuttor.egg-info/dependency_links.txt
bobtemplates.bsuttor.egg-info/namespace_packages.txt
bobtemplates.bsuttor.egg-info/not-zip-safe
bobtemplates.bsuttor.egg-info/requires.txt
bobtemplates.bsuttor.egg-info/top_level.txt
bobtemplates/plone/.gitignore
bobtemplates/plone/.mrbob.ini
bobtemplates/plone/.travis.yml.bob
bobtemplates/plone/CHANGES.txt.bob
bobtemplates/plone/MANIFEST.in.bob
bobtemplates/plone/Makefile.bob
bobtemplates/plone/README.rst.bob
bobtemplates/plone/buildout.cfg.bob
bobtemplates/plone/setup.py.bob
bobtemplates/plone/docs/LICENSE.rst.bob
bobtemplates/plone/src/+package.namespace+/__init__.py
bobtemplates/plone/src/+package.namespace+/+package.name+/__init__.py.bob
bobtemplates/plone/src/+package.namespace+/+package.name+/configure.zcml.bob
bobtemplates/plone/src/+package.namespace+/+package.name+/interfaces.py.bob
bobtemplates/plone/src/+package.namespace+/+package.name+/setuphandlers.py.bob
bobtemplates/plone/src/+package.namespace+/+package.name+/testing.py.bob
bobtemplates/plone/src/+package.namespace+/+package.name+/testing.zcml.bob
bobtemplates/plone/src/+package.namespace+/+package.name+/browser/__init__.py
bobtemplates/plone/src/+package.namespace+/+package.name+/browser/configure.zcml.bob
bobtemplates/plone/src/+package.namespace+/+package.name+/browser/static/.gitkeep
bobtemplates/plone/src/+package.namespace+/+package.name+/locales/+package.namespace+.+package.name+.pot.bob
bobtemplates/plone/src/+package.namespace+/+package.name+/profiles/default/browserlayer.xml.bob
bobtemplates/plone/src/+package.namespace+/+package.name+/profiles/default/metadata.xml
bobtemplates/plone/src/+package.namespace+/+package.name+/profiles/testing/+package.namespace+.+package.name+.txt
bobtemplates/plone/src/+package.namespace+/+package.name+/profiles/testing/metadata.xml.bob
bobtemplates/plone/src/+package.namespace+/+package.name+/profiles/testing/properties.xml.bob
bobtemplates/plone/src/+package.namespace+/+package.name+/tests/__init__.py
bobtemplates/plone/src/+package.namespace+/+package.name+/tests/example.robot.bob
