Metadata-Version: 1.1
Name: bobtemplates.bsuttor
Version: 0.1.1
Summary: Templates by Benoît Suttor.
Home-page: https://github.com/bsuttor/bobtemplates.bsuttor
Author: Benoît Suttor
Author-email: ben.suttor@gmail..com
License: GPL
Keywords: Templates mr.bob Plone
Platform: UNKNOWN
Classifier: Environment :: Console
Classifier: Operating System :: OS Independent
Classifier: Intended Audience :: Developers
Classifier: Natural Language :: English
Classifier: Programming Language :: Python
Classifier: Topic :: Software Development :: Code Generators
Classifier: Topic :: Utilities
